src/__init__.py
src/operations.py
calculator_ps-0.1.0.dist-info/METADATA
calculator_ps-0.1.0.dist-info/WHEEL
calculator_ps-0.1.0.dist-info/top_level.txt
calculator_ps-0.1.0.dist-info/RECORD
